vpe_sitter/__init__.py
vpe_sitter/listen.py
vpe_sitter/parsers.py
vpe_sitter/py.typed
vpe_sitter/sitter.py
vpe_sitter-0.2.1.dist-info/METADATA
vpe_sitter-0.2.1.dist-info/WHEEL
vpe_sitter-0.2.1.dist-info/entry_points.txt
vpe_sitter-0.2.1.dist-info/top_level.txt
vpe_sitter-0.2.1.dist-info/RECORD
