Metadata-Version: 2.4
Name: vpe-sitter
Version: 0.2.1
Summary: Tree-sitter support for Vim
Author-email: Paul Ollis <paul@cleversheep.org>
Classifier: Development Status :: 3 - Alpha
Classifier: License :: OSI Approved :: MIT License
Classifier: Operating System :: POSIX :: Linux
Classifier: Programming Language :: Python :: 3
Classifier: Programming Language :: Python :: 3.11
Classifier: Environment :: Console
Classifier: Topic :: Education
Requires-Python: <3.14,>=3.11
Requires-Dist: vpe>=0.7.3
Requires-Dist: tree-sitter==0.24.0
